aqago_app_sdk/__init__.py
aqago_app_sdk/app.py
aqago_app_sdk/artifact.py
aqago_app_sdk/errors.py
aqago_app_sdk-0.0.6.dist-info/METADATA
aqago_app_sdk-0.0.6.dist-info/WHEEL
aqago_app_sdk-0.0.6.dist-info/licenses/LICENSE
aqago_app_sdk-0.0.6.dist-info/RECORD
