Metadata-Version: 2.4
Name: aqago-app-sdk
Version: 0.0.6
Summary: The Aqago App SDK
Project-URL: Homepage, https://github.com/aqa-technologies/aqago-app-sdk-python
Project-URL: Issues, https://github.com/aqa-technologies/aqago-app-sdk-python/issues
Author-email: Aqa Engineering <engineering@aqago.com>
License-Expression: BUSL-1.1
License-File: LICENSE
Classifier: Operating System :: OS Independent
Classifier: Programming Language :: Python :: 3
Requires-Python: >=3.11
Requires-Dist: pytest-mock>=3.14.0
Requires-Dist: pytest>=8.3.5
